numerblox/__init__.py
numerblox/download.py
numerblox/ensemble.py
numerblox/evaluation.py
numerblox/feature_groups.py
numerblox/meta.py
numerblox/misc.py
numerblox/model_upload.py
numerblox/models.py
numerblox/neutralizers.py
numerblox/numerframe.py
numerblox/penalizers.py
numerblox/prediction_loaders.py
numerblox/submission.py
numerblox/targets.py
numerblox/preprocessing/__init__.py
numerblox/preprocessing/base.py
numerblox/preprocessing/classic.py
numerblox/preprocessing/signals.py
numerblox-1.6.1.dist-info/licenses/LICENSE
numerblox-1.6.1.dist-info/METADATA
numerblox-1.6.1.dist-info/WHEEL
numerblox-1.6.1.dist-info/top_level.txt
numerblox-1.6.1.dist-info/RECORD
