Metadata-Version: 2.4
Name: numerblox
Version: 1.6.1
Summary: Solid Numerai Pipelines
Author-email: CrowdCent <support@crowdcent.com>
License: MIT License
Requires-Python: <4,>=3.10
License-File: LICENSE
Requires-Dist: tqdm>=4.66.1
Requires-Dist: numpy>=1.26.3
Requires-Dist: scipy>=1.10.0
Requires-Dist: pandas>=2.1.1
Requires-Dist: pandas-ta-classic>=0.3.14b
Requires-Dist: joblib>=1.3.2
Requires-Dist: pyarrow>=14.0.1
Requires-Dist: numerapi>=2.19.1
Requires-Dist: matplotlib>=3.4.0
Requires-Dist: scikit-learn>=1.6.1
Requires-Dist: python-dateutil>=2.8.2
Requires-Dist: google-cloud-storage>=2.11.0
Requires-Dist: numerai-era-data>=0.1.1
Requires-Dist: numerai-tools>=0.2.2
Requires-Dist: polars>=1.5.0
Requires-Dist: werkzeug>=3.0.3
Provides-Extra: test
Requires-Dist: pytest<8.0.0,>=7.4.2; extra == "test"
Requires-Dist: pytest-cov<5.0.0,>=4.1.0; extra == "test"
Requires-Dist: pytest-mock<4.0.0,>=3.11.1; extra == "test"
Requires-Dist: mkdocs<2.0.0,>=1.5.3; extra == "test"
Requires-Dist: mkdocs-material<10.0.0,>=9.4.2; extra == "test"
Requires-Dist: eod<1.0.0,>=0.2.1; extra == "test"
Requires-Dist: kaggle<2.0.0,>=1.5.16; extra == "test"
Requires-Dist: scikit-lego>=0.9.1; extra == "test"
Requires-Dist: xgboost>=2.0.0; extra == "test"
Requires-Dist: mkdocstrings-python<2.0.0,>=1.7.1; extra == "test"
Requires-Dist: ruff>=0.3.0; extra == "test"
Dynamic: license-file
